reqbar
