Metadata-Version: 1.0
Name: reqbar
Version: 1.0.6
Summary: To install python package requirements with a bar rather logs!
Home-page: UNKNOWN
Author: Muhammad Ali
Author-email: malirashid1994@gmail.com
License: UNKNOWN
Platform: UNKNOWN
